{
  "$schema": "https://developer.microsoft.com/json-schemas/spfx-build/package-solution.schema.json",
  "solution": {
    "name": "list-view-command-client-side-solution",
    "id": "3ef7aa82-e9a4-4ab4-956b-957b14c9e583",
    "version": "1.0.0.0",
    "includeClientSideAssets": true,
    "isDomainIsolated": false,
    "features": [
      {
        "title": "Application Extension - Deployment of custom action.",
        "description": "Deploys a custom action with ClientSideComponentId association",
        "id": "18ad0299-8130-4b25-a760-bd86cc678753",
        "version": "1.0.0.0",
        "assets": {
          "elementManifests": [
            "elements.xml",
            "clientsideinstance.xml"
          ]
        }
      }
    ]
  },
  "paths": {
    "zippedPackage": "solution/list-view-command.sppkg"
  }
}